xsstrike_reborn.py
xsstrike_reborn-4.1.0.dist-info/entry_points.txt
xsstrike_reborn-4.1.0.dist-info/LICENSE
xsstrike_reborn-4.1.0.dist-info/WHEEL
xsstrike_reborn-4.1.0.dist-info/METADATA
xsstrike_reborn-4.1.0.dist-info/RECORD
