Metadata-Version: 2.1
Name: xsstrike_reborn
Version: 4.1.0
Summary: Updated fork of XSStrike: The most advanced XSS scanner.
Author-email: s0md3v <s0md3v@gmail.com>, ItsIgnacioPortal <5990@protonmail.com>
Requires-Python: >=3.0
Classifier: License :: OSI Approved :: GNU General Public License v3 or later (GPLv3+)
Classifier: Development Status :: 4 - Beta
Classifier: Programming Language :: Python :: 3 :: Only
Classifier: Programming Language :: Python :: 3
Classifier: Programming Language :: Python :: 3.7
Classifier: Programming Language :: Python :: 3.8
Classifier: Programming Language :: Python :: 3.9
Classifier: Programming Language :: Python :: 3.10
Classifier: Programming Language :: Python :: 3.11
Classifier: Intended Audience :: Information Technology
Classifier: Intended Audience :: Developers
Classifier: Intended Audience :: System Administrators
Classifier: Natural Language :: English
Classifier: Topic :: Security
Project-URL: Home, https://github.com/ItsIgnacioPortal/XSStrike-Reborn
